g200s/__init__.py
g200s/exceptions.py
g200s/teapot.py
g200s-0.0.2.dist-info/METADATA
g200s-0.0.2.dist-info/RECORD
g200s-0.0.2.dist-info/WHEEL
g200s-0.0.2.dist-info/top_level.txt
