Metadata-Version: 2.1
Name: g200s
Version: 0.0.2
Summary: Python module for interacting with Ready For Sky Skykettle G200S Teapot
Home-page: https://github.com/w1r0x/g200s
Author: Denis Ryabyy
Author-email: vv1r0x@gmail.com
License: UNKNOWN
Keywords: r4s,g200s,skykettle,bluetooth
Platform: UNKNOWN
Classifier: Programming Language :: Python :: 3
Requires-Dist: bluepy
